streamlit_plugins/__init__.py
streamlit_plugins/components/__init__.py
streamlit_plugins/components/annotated_text/__init__.py
streamlit_plugins/components/input_chat_advance/__init__.py
streamlit_plugins/components/label_studio/__init__.py
streamlit_plugins/components/label_studio/frontend/build/asset-manifest.json
streamlit_plugins/components/label_studio/frontend/build/bootstrap.min.css
streamlit_plugins/components/label_studio/frontend/build/custom.css
streamlit_plugins/components/label_studio/frontend/build/index.html
streamlit_plugins/components/label_studio/frontend/build/static/css/2.4f758a59.chunk.css
streamlit_plugins/components/label_studio/frontend/build/static/css/2.4f758a59.chunk.css.map
streamlit_plugins/components/label_studio/frontend/build/static/js/2.524324ba.chunk.js
streamlit_plugins/components/label_studio/frontend/build/static/js/2.524324ba.chunk.js.LICENSE.txt
streamlit_plugins/components/label_studio/frontend/build/static/js/2.524324ba.chunk.js.map
streamlit_plugins/components/label_studio/frontend/build/static/js/main.34b82d10.chunk.js
streamlit_plugins/components/label_studio/frontend/build/static/js/main.34b82d10.chunk.js.map
streamlit_plugins/components/label_studio/frontend/build/static/js/runtime-main.65660c44.js
streamlit_plugins/components/label_studio/frontend/build/static/js/runtime-main.65660c44.js.map
streamlit_plugins/components/loader/__init__.py
streamlit_plugins/components/navbar/__init__.py
streamlit_plugins/components/navbar/config.py
streamlit_plugins/components/navbar/inject_script.py
streamlit_plugins/components/navbar/frontend/build/CrossOriginInterface.js
streamlit_plugins/components/navbar/frontend/build/asset-manifest.json
streamlit_plugins/components/navbar/frontend/build/bootstrap.min.css
streamlit_plugins/components/navbar/frontend/build/bootstrap.min.css.map
streamlit_plugins/components/navbar/frontend/build/index.html
streamlit_plugins/components/navbar/frontend/build/material-fonts.css
streamlit_plugins-0.7.7.dist-info/licenses/LICENSE
streamlit_plugins-0.7.7.dist-info/METADATA
streamlit_plugins-0.7.7.dist-info/WHEEL
streamlit_plugins-0.7.7.dist-info/top_level.txt
streamlit_plugins-0.7.7.dist-info/RECORD
