Metadata-Version: 2.4
Name: streamlit-plugins
Version: 0.7.7
Summary: Components and Frameworks to give new features to streamlit
Home-page: https://github.com/quiradev/streamlit-plugins
Author: Victor Quilon Ranera
Author-email: v.quilonr@gmail.com
License: MIT
Keywords: streamlit,plugins,framework,components,navbar,loader,multilit
Classifier: Intended Audience :: Developers
Classifier: Programming Language :: Python
Classifier: Programming Language :: Python :: 3.9
Classifier: Programming Language :: Python :: 3.10
Classifier: Programming Language :: Python :: 3.11
Requires-Python: >=3.9
License-File: LICENSE
Requires-Dist: streamlit<2,>=1.38.0
Requires-Dist: compress-pickle>=2.1.0
Requires-Dist: bokeh>=3.1.1
Requires-Dist: validators>=0.22.0
Requires-Dist: pandas>=2.2.0
Requires-Dist: htbuilder
Requires-Dist: webcolors
Requires-Dist: pydantic
Dynamic: author
Dynamic: author-email
Dynamic: classifier
Dynamic: description
Dynamic: description-content-type
Dynamic: home-page
Dynamic: keywords
Dynamic: license
Dynamic: license-file
Dynamic: requires-dist
Dynamic: requires-python
Dynamic: summary
